openfgl/__init__.py
openfgl/config.py
openfgl/data/__init__.py
openfgl/data/distributed_dataset_loader.py
openfgl/data/global_dataset_loader.py
openfgl/data/processing.py
openfgl/data/simulation.py
openfgl/flcore/__init__.py
openfgl/flcore/base.py
openfgl/flcore/trainer.py
openfgl/flcore/adafgl/__init__.py
openfgl/flcore/adafgl/_utils.py
openfgl/flcore/adafgl/adafgl_config.py
openfgl/flcore/adafgl/adafgl_models.py
openfgl/flcore/adafgl/client.py
openfgl/flcore/adafgl/label_propagation_models.py
openfgl/flcore/adafgl/op.py
openfgl/flcore/adafgl/server.py
openfgl/flcore/adafgl/csrc/libcudamatmul.so
openfgl/flcore/adafgl/csrc/libmatmul.so
openfgl/flcore/fedavg/__init__.py
openfgl/flcore/fedavg/client.py
openfgl/flcore/fedavg/server.py
openfgl/flcore/feddc/__init__.py
openfgl/flcore/feddc/client.py
openfgl/flcore/feddc/feddc_config.py
openfgl/flcore/feddc/server.py
openfgl/flcore/feddep/__init__.py
openfgl/flcore/feddep/_utils.py
openfgl/flcore/feddep/client.py
openfgl/flcore/feddep/feddep_config.py
openfgl/flcore/feddep/localdep.py
openfgl/flcore/feddep/server.py
openfgl/flcore/feddep/dec_cluster/clustering.py
openfgl/flcore/feddep/dec_cluster/ptdec/cluster.py
openfgl/flcore/feddep/dec_cluster/ptdec/dec.py
openfgl/flcore/feddep/dec_cluster/ptdec/model.py
openfgl/flcore/feddep/dec_cluster/ptdec/utils.py
openfgl/flcore/feddep/dec_cluster/ptsdae/dae.py
openfgl/flcore/feddep/dec_cluster/ptsdae/model.py
openfgl/flcore/feddep/dec_cluster/ptsdae/sdae.py
openfgl/flcore/feddep/dec_cluster/ptsdae/sklearn_api.py
openfgl/flcore/feddep/dec_cluster/ptsdae/utils.py
openfgl/flcore/fedgl/__init__.py
openfgl/flcore/fedgl/client.py
openfgl/flcore/fedgl/fedgl_config.py
openfgl/flcore/fedgl/models.py
openfgl/flcore/fedgl/server.py
openfgl/flcore/fedgta/__init__.py
openfgl/flcore/fedgta/_utils.py
openfgl/flcore/fedgta/client.py
openfgl/flcore/fedgta/fedgta_config.py
openfgl/flcore/fedgta/server.py
openfgl/flcore/fedproto/__init__.py
openfgl/flcore/fedproto/client.py
openfgl_python-1.0.3.dist-info/METADATA
openfgl_python-1.0.3.dist-info/WHEEL
openfgl_python-1.0.3.dist-info/licenses/LICENSE
openfgl_python-1.0.3.dist-info/RECORD
